weaponx
