Metadata-Version: 2.1
Name: weaponx
Version: 0.6
Summary: boom
Home-page: https://github.com/somewheve/flux
Author: somewheve
Author-email: somewheve@gmail.com
License: UNKNOWN
Platform: UNKNOWN
